<?xml version="1.0" encoding="UTF-8" ?>
<!DOCTYPE mapper PUBLIC "-//mybatis.org//DTD Mapper 3.0//EN" "http://mybatis.org/dtd/mybatis-3-mapper.dtd">
<mapper namespace="com.state.dao.sys.SysConfigDaoI">

	<insert id="insert" parameterType="PfLoginCountPo">
		INSERT INTO <include refid='public.model' />PF_LOGIN_COUNT
		(ID_
		,DOC_CREATED_
		,IP_
		,COUNT_
		,USER_ID_)
		VALUES(
		#{id ,jdbcType=VARCHAR},
		#{docCreated, jdbcType=TIMESTAMP},
		#{ip, jdbcType=VARCHAR},
		#{count ,jdbcType=INTEGER},
		#{userId ,jdbcType=VARCHAR}
		)
	</insert>
	
	
	<insert id="insertSysConfig" parameterType="PfSysConfigPo">
INSERT INTO <include refid='public.model' />PF_SYS_CONFIG(
ID_,
KEY_,
VALUE_,
ADD_NAME_,
ADD_NAME_CN_,
REMARK_,
DOC_CREATED_,
TYPE_) VALUES(
#{id ,jdbcType=VARCHAR},
#{key ,jdbcType=VARCHAR},
#{value ,jdbcType=VARCHAR},
#{addName ,jdbcType=VARCHAR},
#{addNameCn ,jdbcType=VARCHAR},
#{remark ,jdbcType=VARCHAR},
#{docCreated, jdbcType=TIMESTAMP},
#{type, jdbcType=VARCHAR});

	</insert>
	
	<update id="updateSysConfig" parameterType="PfSysConfigPo">
		UPDATE <include refid='public.model' /> PF_SYS_CONFIG 
		<set> 
			ID_=#{id,jdbcType=VARCHAR},
			KEY_=#{key,jdbcType=VARCHAR},
			VALUE_=#{value,jdbcType=VARCHAR},
			LAST_MODIFIER_ = #{lastModifier, jdbcType=VARCHAR},
      		LAST_MODIFIER_CN_ = #{lastModifierCn, jdbcType=VARCHAR},
      		LAST_MODIFIED_ = #{lastModified, jdbcType=TIMESTAMP},
      		REMARK_ = #{remark, jdbcType=VARCHAR},
			TYPE_ = #{type,jdbcType=VARCHAR}
		</set> 
		where ID_=#{id}

	</update>
	
	<resultMap id="ResultMap" type="PfSysConfigPo">
		<id property="id" column="ID_" jdbcType="VARCHAR" />
		<result property="docCreated" column="DOC_CREATED_" jdbcType="TIMESTAMP" />
		<result property="lastModified" column="LAST_MODIFIED_" jdbcType="TIMESTAMP" />
		<result property="key" column="KEY_" jdbcType="VARCHAR" />
		<result property="type" column="TYPE_" jdbcType="VARCHAR" />
		<result property="value" column="VALUE_" jdbcType="INTEGER" />
		<result property="remark" column="REMARK_" jdbcType="VARCHAR" />
	</resultMap>

	

	<select id="selectOne" resultMap="ResultMap">
		select top 1 * from <include refid='public.model' /> PF_SYS_CONFIG where KEY_ = #{key, jdbcType=VARCHAR}
	</select>
	<select id="selectOneByType" resultMap="ResultMap">
		select * from <include refid='public.model' /> PF_SYS_CONFIG where TYPE_ = #{key, jdbcType=VARCHAR}
		<if test="mdate!=null and mdate!=''">
			 and KEY_=#{mdate}
		</if>
	</select>
	<select id="selectListByType" resultMap="ResultMap">
		select  * from <include refid='public.model' /> PF_SYS_CONFIG where TYPE_ = #{type, jdbcType=VARCHAR}
	</select>
	
	
	
</mapper>